Metadata-Version: 2.1
Name: impauto
Version: 1.0.2
Summary: Make your life easier with automated inputs
Home-page: https://github.com/Edhyjox/impauto
Author: Edhyjox
Author-email: Edhyjox@gmail.com
License: MIT
Platform: UNKNOWN
Classifier: License :: OSI Approved :: MIT License
Classifier: Programming Language :: Python :: 3.6
Classifier: Programming Language :: Python :: 3.7
Classifier: Programming Language :: Python :: 3.8
